setup.py
distributions_bindupillai/Binomialdistribution.py
distributions_bindupillai/Gaussiandistribution.py
distributions_bindupillai/Generaldistribution.py
distributions_bindupillai/__init__.py
distributions_bindupillai.egg-info/PKG-INFO
distributions_bindupillai.egg-info/SOURCES.txt
distributions_bindupillai.egg-info/dependency_links.txt
distributions_bindupillai.egg-info/not-zip-safe
distributions_bindupillai.egg-info/top_level.txt